datable_ai/__init__.py
datable_ai/core/__init__.py
datable_ai/core/llm.py
datable_ai/output.py
datable_ai/structured_output.py
datable_ai-0.0.6.dist-info/LICENSE
datable_ai-0.0.6.dist-info/METADATA
datable_ai-0.0.6.dist-info/WHEEL
datable_ai-0.0.6.dist-info/RECORD
